{
  "features": [
    {
      "type": "Feature",
      "properties": {
        "id": "marker-iq07e6z90",
        "title": "22 Rue de Strasbourg",
        "description": "<p>22 Rue de Strasbourg 44000 Nantes</p>\n<p>Tél. +33 (0) 253 453 554</p>\n<p><strong>Horaires:</strong></p>\n<p>Lundi - Samedi: 10h00 - 12h00 / 14h00 - 19h00</p>\n<p>Dimanche fermer</p>\n",
        "marker-size": "medium",
        "marker-color": "#1087bf",
        "marker-symbol": ""
      },
      "geometry": {
        "coordinates": [
          -1.551886,
          47.216858
        ],
        "type": "Point"
      },
      "id": "0b5a32673c18c82f69932435bb9df0f7"
    },
    {
      "type": "Feature",
      "properties": {
        "id": "marker-iq07f6qa1",
        "title": "Place de la Trinité",
        "description": "<p>2 Place de la Trinité 35000 RENNES</p>\n<p>Tél. +33 (0) 256 519 606</p>\n<p><strong>Horaires:</strong></p>\n<p>Lundi - Samedi: 10h00 - 12h00 / 14h00 - 19h00</p>\n<p>Dimanche fermer</p>",
        "marker-size": "medium",
        "marker-color": "#1087bf",
        "marker-symbol": ""
      },
      "geometry": {
        "coordinates": [
          -1.68359,
          48.112458
        ],
        "type": "Point"
      },
      "id": "879f07c526a46727bceefd13401b3297"
    }
  ],
  "type": "FeatureCollection"
}