{
  "features": [
    {
      "type": "Feature",
      "properties": {
        "id": "marker-iryd06b60",
        "title": "91 Boulevard Bessières",
        "description": "<p><br /> Adresse: 91 Boulevard Bessières, 75017 Paris<br /> \nTel: aucun</p>\n<p><strong>Horaire</strong></p>\n<ul>\n<li>non indiquer</li>\n</ul>",
        "marker-size": "medium",
        "marker-color": "#1087bf",
        "marker-symbol": ""
      },
      "geometry": {
        "coordinates": [
          2.318886,
          48.896129
        ],
        "type": "Point"
      },
      "id": "dc932eef21e30c0109634a49a5ab0ade"
    }
  ],
  "type": "FeatureCollection"
}